{
    "fluentMethods": true,
    "clientRootFolder": "",
    "relationships": [
        {
            "relationshipName": "participant",
            "otherEntityName": "participant",
            "relationshipType": "one-to-one",
            "relationshipValidateRules": [],
            "otherEntityField": "id",
            "ownerSide": true,
            "useJPADerivedIdentifier": false,
            "otherEntityRelationshipName": "studyId"
        }
    ],
    "fields": [
        {
            "fieldName": "code",
            "fieldType": "String",
            "fieldValidateRules": [
                "required",
                "unique"
            ]
        }
    ],
    "changelogDate": "20210210150449",
    "dto": "no",
    "searchEngine": false,
    "service": "no",
    "entityTableName": "study_id",
    "databaseType": "sql",
    "readOnly": false,
    "jpaMetamodelFiltering": false,
    "pagination": "no"
}
