{
    "fluentMethods": true,
    "clientRootFolder": "",
    "relationships": [],
    "fields": [
        {
            "fieldName": "risk_factor",
            "fieldType": "Double",
            "fieldValidateRules": [
                "required"
            ]
        },
        {
            "fieldName": "year",
            "fieldType": "Integer",
            "fieldValidateRules": [
                "required"
            ]
        }
    ],
    "changelogDate": "20210219085250",
    "dto": "no",
    "searchEngine": false,
    "service": "serviceImpl",
    "entityTableName": "yearly_risk",
    "databaseType": "sql",
    "readOnly": false,
    "jpaMetamodelFiltering": false,
    "pagination": "no"
}
